informeren/__init__.py
informeren/epub.py
informeren/version.py
informeren/template/mimetype
informeren/template/EPUB/package.opf
informeren/template/EPUB/xhtml/article.xhtml
informeren/template/EPUB/xhtml/frontpage.xhtml
informeren/template/EPUB/xhtml/nav.xhtml
informeren/template/META-INF/container.xml
informeren_dagens_epub-1.0.2.dist-info/METADATA
informeren_dagens_epub-1.0.2.dist-info/RECORD
informeren_dagens_epub-1.0.2.dist-info/WHEEL
informeren_dagens_epub-1.0.2.dist-info/entry_points.txt
informeren_dagens_epub-1.0.2.dist-info/top_level.txt
